pwr_tray/IniTool.py
pwr_tray/SwayIdleMgr.py
pwr_tray/Utils.py
pwr_tray/YamlDump.py
pwr_tray/__init__.py
pwr_tray/main.py
pwr_tray/resources/FullSun-v03.svg
pwr_tray/resources/GoingDown-v03.svg
pwr_tray/resources/PlayingNow-v03.svg
pwr_tray/resources/RisingMoon-v03.svg
pwr_tray/resources/SettingSun-v03.svg
pwr_tray/resources/StopSign-v03.svg
pwr_tray/resources/Unlocked-v03.svg
pwr_tray/resources/UnlockedMoon-v03.svg
pwr_tray/resources/__init__.py
pwr_tray/resources/lockpaper.png
pwr_tray/resources/SetA/pwr-inh-v03.svg
pwr_tray/resources/SetA/pwr-no-sleep-v03.svg
pwr_tray/resources/SetA/pwr-uninh-v03.svg
pwr_tray/resources/SetB/LoBattery-v03.svg
pwr_tray/resources/SetB/LockOnlyMode-v03.svg
pwr_tray/resources/SetB/NormMode-v03.svg
pwr_tray/resources/SetC/New-LockOnly-v03.svg
pwr_tray/resources/SetC/New-LowBattery-v03.svg
pwr_tray/resources/SetC/New-NormMode-v03.svg
pwr_tray/resources/SetC/New-PresMode-v03.svg
pwr_tray-1.0.2.dist-info/entry_points.txt
pwr_tray-1.0.2.dist-info/licenses/LICENSE
pwr_tray-1.0.2.dist-info/WHEEL
pwr_tray-1.0.2.dist-info/METADATA
pwr_tray-1.0.2.dist-info/RECORD
