Metadata-Version: 2.4
Name: pwr_tray
Version: 1.0.2
Summary: A GTK tray applet for power management for i3/sway/KDE
Keywords: power,energy,GTK,applet,tray,kde,i3wm,sway
Author-email: Joe Defen <joedef@google.com>
Requires-Python: >=3.8
Classifier: Programming Language :: Python :: 3
Classifier: License :: OSI Approved :: MIT License
Classifier: Operating System :: POSIX :: Linux
License-File: LICENSE
Requires-Dist: importlib-metadata; python_version<"3.8"
Requires-Dist: psutil>=5.9
Requires-Dist: PyQt5>=5.15
Project-URL: Bug Tracker, https://github.com/joedefen/pwr-tray/issues
Project-URL: Homepage, https://github.com/joedefen/pwr-tray
